mldali/__init__.py
mldali/__version__.py
mldali/const.py
mldali/controller.py
mldali/light.py
mldali/shade.py
python_ml_dali-0.0.16.dist-info/LICENSE
python_ml_dali-0.0.16.dist-info/METADATA
python_ml_dali-0.0.16.dist-info/WHEEL
python_ml_dali-0.0.16.dist-info/top_level.txt
python_ml_dali-0.0.16.dist-info/RECORD
