Metadata-Version: 2.1
Name: python-ml-dali
Version: 0.0.16
Summary: A Python library to communicate with Dali controllers from Ministry of Light.
Home-page: https://github.com/benoitdepaire/python-ml-dali
Author: Benoit Depaire
Author-email: benoit@depaire.net
License: GNU GPLv3
Classifier: Programming Language :: Python :: 3
Classifier: Programming Language :: Python :: 3.8
Classifier: Development Status :: 2 - Pre-Alpha
Classifier: Framework :: AsyncIO
Classifier: Intended Audience :: Developers
Classifier: License :: OSI Approved :: GNU General Public License v3 (GPLv3)
Classifier: Natural Language :: English
Classifier: Topic :: Software Development :: Libraries :: Python Modules
Requires-Python: >=3.8
License-File: LICENSE
Requires-Dist: asyncio
Requires-Dist: pyserial
Requires-Dist: aioserial
